timedata.cp35-win32.pyd
timedata-0.8.dist-info/DESCRIPTION.rst
timedata-0.8.dist-info/METADATA
timedata-0.8.dist-info/RECORD
timedata-0.8.dist-info/WHEEL
timedata-0.8.dist-info/metadata.json
timedata-0.8.dist-info/top_level.txt
timedata_tests/ColorList_test.py
timedata_tests/Color_test.py
timedata_tests/Driver.py
timedata_tests/General_test.py
timedata_tests/Generated_test.py
timedata_tests/Operations_test.py
timedata_tests/__init__.py
timedata_tests/benchmarks.py
timedata_tests/tiny_benchmark.py
