Metadata-Version: 2.0
Name: timedata
Version: 0.8
Summary: High-performance arithmetic for RGB color and for time data in general.
Home-page: https://github.com/rec/timedata
Author: Tom Swirly
Author-email: tom@swirly.com
License: UNKNOWN
Download-URL: https://github.com/rec/timedata/releases/tag/v0.8
Keywords: color,cython,dsp,C++
Platform: UNKNOWN
